validlink/__init__.py
validlink/checker.py
validlink-0.2.dist-info/LICENSE
validlink-0.2.dist-info/METADATA
validlink-0.2.dist-info/WHEEL
validlink-0.2.dist-info/top_level.txt
validlink-0.2.dist-info/RECORD
