Metadata-Version: 2.1
Name: validlink
Version: 0.2
Summary: A simple URL validity checker
Home-page: https://mrfidal.in/basic-pip-package/validlink
Author: Fidal
Author-email: mrfidal@proton.me
Classifier: Programming Language :: Python :: 3
Classifier: License :: OSI Approved :: MIT License
Classifier: Operating System :: OS Independent
Requires-Python: >=3.6
License-File: LICENSE
Requires-Dist: requests
